abi_pyspark_utils/__init__.py
abi_pyspark_utils/spark.py
abi_pyspark_utils-0.1.4.dist-info/WHEEL
abi_pyspark_utils-0.1.4.dist-info/METADATA
abi_pyspark_utils-0.1.4.dist-info/RECORD
