Metadata-Version: 2.1
Name: abi-pyspark-utils
Version: 0.1.4
Summary: 
Author: PVH
Requires-Python: ==3.8.8
Classifier: Programming Language :: Python :: 3
Requires-Dist: pyarrow (>=7.0.0,<8.0.0)
Requires-Dist: pyspark (==3.1.1)
